Metadata-Version: 2.1
Name: cernopendata-client
Version: 1.0.1
Summary: cernopendata-client.
Author: CERN Open Data
Author-email: opendata-team@cern.ch
Classifier: Development Status :: 4 - Beta
Classifier: Environment :: Web Environment
Classifier: Intended Audience :: Developers
Classifier: License :: OSI Approved :: GNU General Public License v3 (GPLv3)
Classifier: Operating System :: OS Independent
Classifier: Programming Language :: Python :: 3
Classifier: Programming Language :: Python :: 3.8
Classifier: Programming Language :: Python :: 3.9
Classifier: Programming Language :: Python :: 3.10
Classifier: Programming Language :: Python :: 3.11
Classifier: Programming Language :: Python :: 3.12
Classifier: Programming Language :: Python :: 3.13
Classifier: Programming Language :: Python :: 3.14
Classifier: Programming Language :: Python :: Implementation :: CPython
Classifier: Programming Language :: Python
Classifier: Topic :: Internet :: WWW/HTTP :: Dynamic Content
Classifier: Topic :: Software Development :: Libraries :: Python Modules
Classifier: Topic :: System :: Archiving
Requires-Python: >=3.8
License-File: LICENSE
License-File: AUTHORS.md
Requires-Dist: click>=7
Requires-Dist: requests>=2
Provides-Extra: docs
Requires-Dist: myst-parser; extra == "docs"
Requires-Dist: jinja2<3.1.0; extra == "docs"
Requires-Dist: Sphinx>=1.4.4; extra == "docs"
Requires-Dist: sphinx-rtd-theme>=0.1.9; extra == "docs"
Requires-Dist: sphinx-click>=2.5.0; extra == "docs"
Provides-Extra: pycurl
Requires-Dist: pycurl>=7; extra == "pycurl"
Provides-Extra: tests
Requires-Dist: black>=19.10b0; extra == "tests"
Requires-Dist: check-manifest>=0.25; extra == "tests"
Requires-Dist: coverage>=4.0; extra == "tests"
Requires-Dist: mock>=3.0; extra == "tests"
Requires-Dist: pydocstyle>=1.0.0; extra == "tests"
Requires-Dist: pytest-cov>=1.8.0; extra == "tests"
Requires-Dist: pytest>=2.8.0; extra == "tests"
Requires-Dist: pytest-mock>=3.0; extra == "tests"
Provides-Extra: xrootd
Requires-Dist: xrootd>=4.12.2; extra == "xrootd"
Provides-Extra: all
Requires-Dist: myst-parser; extra == "all"
Requires-Dist: jinja2<3.1.0; extra == "all"
Requires-Dist: Sphinx>=1.4.4; extra == "all"
Requires-Dist: sphinx-rtd-theme>=0.1.9; extra == "all"
Requires-Dist: sphinx-click>=2.5.0; extra == "all"
Requires-Dist: pycurl>=7; extra == "all"
Requires-Dist: black>=19.10b0; extra == "all"
Requires-Dist: check-manifest>=0.25; extra == "all"
Requires-Dist: coverage>=4.0; extra == "all"
Requires-Dist: mock>=3.0; extra == "all"
Requires-Dist: pydocstyle>=1.0.0; extra == "all"
Requires-Dist: pytest-cov>=1.8.0; extra == "all"
Requires-Dist: pytest>=2.8.0; extra == "all"
Requires-Dist: pytest-mock>=3.0; extra == "all"
Requires-Dist: xrootd>=4.12.2; extra == "all"
Requires-Dist: myst-parser; extra == "all"
Requires-Dist: jinja2<3.1.0; extra == "all"
Requires-Dist: Sphinx>=1.4.4; extra == "all"
Requires-Dist: sphinx-rtd-theme>=0.1.9; extra == "all"
Requires-Dist: sphinx-click>=2.5.0; extra == "all"
Requires-Dist: pycurl>=7; extra == "all"
Requires-Dist: black>=19.10b0; extra == "all"
Requires-Dist: check-manifest>=0.25; extra == "all"
Requires-Dist: coverage>=4.0; extra == "all"
Requires-Dist: mock>=3.0; extra == "all"
Requires-Dist: pydocstyle>=1.0.0; extra == "all"
Requires-Dist: pytest-cov>=1.8.0; extra == "all"
Requires-Dist: pytest>=2.8.0; extra == "all"
Requires-Dist: pytest-mock>=3.0; extra == "all"
Requires-Dist: xrootd>=4.12.2; extra == "all"
